{"stats":{"minecraft:picked_up":{"minecraft:blue_wool":4,"minecraft:lime_wool":59,"minecraft:end_stone":15,"minecraft:yellow_wool":1,"minecraft:red_wool":26,"minecraft:oak_wood":43,"minecraft:stone_sword":3,"minecraft:diamond":44,"minecraft:iron_ingot":3262,"minecraft:yellow_terracotta":4,"minecraft:gold_ingot":1195,"minecraft:emerald":34,"minecraft:wet_sponge":1},"minecraft:used":{"minecraft:water_bucket":1,"minecraft:blue_terracotta":64,"minecraft:stone_sword":9,"minecraft:red_wool":153,"minecraft:lime_wool":188,"minecraft:blue_wool":84,"minecraft:red_terracotta":16,"minecraft:iron_sword":20,"minecraft:pink_wool":12,"minecraft:yellow_wool":104,"minecraft:light_gray_wool":38,"minecraft:golden_apple":6,"minecraft:diamond_sword":9,"minecraft:wooden_sword":5,"minecraft:bow":116,"minecraft:yellow_terracotta":4,"minecraft:tnt":15,"minecraft:light_blue_wool":13,"minecraft:oak_wood":197,"minecraft:sponge":1,"minecraft:end_stone":105,"minecraft:shears":78,"minecraft:snowball":1},"minecraft:dropped":{"minecraft:stone_sword":3,"minecraft:gold_ingot":2},"minecraft:custom":{"minecraft:time_since_rest":3355,"minecraft:walk_one_cm":373399,"minecraft:sprint_one_cm":509481,"minecraft:open_enderchest":35,"minecraft:damage_taken":135469,"minecraft:damage_absorbed":240,"minecraft:drop":4,"minecraft:damage_dealt":1504,"minecraft:damage_dealt_absorbed":314,"minecraft:fly_one_cm":685910,"minecraft:player_kills":7,"minecraft:open_chest":30,"minecraft:crouch_one_cm":66085,"minecraft:play_time":195519,"minecraft:deaths":25,"minecraft:sneak_time":19514,"minecraft:jump":2974,"minecraft:leave_game":28,"minecraft:walk_on_water_one_cm":1780,"minecraft:time_since_death":3353,"minecraft:total_world_time":195519,"minecraft:fall_one_cm":74137,"minecraft:inspect_dispenser":1},"minecraft:killed_by":{"minecraft:player":16},"minecraft:mined":{"minecraft:red_wool":6,"minecraft:oak_wood":1,"minecraft:wet_sponge":1,"minecraft:lime_wool":77,"minecraft:blue_wool":2}},"DataVersion":3463}