{"stats":{"minecraft:picked_up":{"minecraft:diamond":26,"minecraft:iron_ingot":586,"minecraft:gold_ingot":197,"minecraft:emerald":20},"minecraft:custom":{"minecraft:time_since_rest":12470,"minecraft:open_chest":13,"minecraft:crouch_one_cm":6224,"minecraft:damage_taken":20828,"minecraft:play_time":103992,"minecraft:sprint_one_cm":235497,"minecraft:open_enderchest":17,"minecraft:walk_one_cm":57102,"minecraft:deaths":3,"minecraft:sneak_time":2184,"minecraft:walk_under_water_one_cm":403,"minecraft:drop":5,"minecraft:jump":1408,"minecraft:damage_dealt":1069,"minecraft:leave_game":6,"minecraft:walk_on_water_one_cm":565,"minecraft:time_since_death":12469,"minecraft:total_world_time":103992,"minecraft:damage_dealt_absorbed":14,"minecraft:swim_one_cm":3090,"minecraft:fall_one_cm":36427,"minecraft:fly_one_cm":375544,"minecraft:player_kills":7},"minecraft:killed_by":{"minecraft:player":3},"minecraft:used":{"minecraft:light_gray_wool":42,"minecraft:wooden_sword":5,"minecraft:stone_sword":11,"minecraft:potion":2,"minecraft:tnt":4,"minecraft:light_blue_wool":77,"minecraft:iron_sword":12},"minecraft:dropped":{"minecraft:iron_ingot":18,"minecraft:gold_ingot":9}},"DataVersion":3463}