{"stats":{"minecraft:mined":{"minecraft:oak_wood":1,"minecraft:yellow_wool":2,"minecraft:white_wool":1},"minecraft:picked_up":{"minecraft:oak_wood":5,"minecraft:iron_ingot":402,"minecraft:gold_ingot":110,"minecraft:emerald":1,"minecraft:white_wool":28},"minecraft:custom":{"minecraft:open_chest":13,"minecraft:time_since_rest":13588,"minecraft:damage_absorbed":161,"minecraft:crouch_one_cm":6192,"minecraft:play_time":33677,"minecraft:sprint_one_cm":98013,"minecraft:walk_one_cm":50126,"minecraft:damage_taken":32517,"minecraft:deaths":12,"minecraft:sneak_time":3553,"minecraft:jump":861,"minecraft:damage_dealt":1419,"minecraft:leave_game":1,"minecraft:time_since_death":13586,"minecraft:total_world_time":33677,"minecraft:damage_dealt_absorbed":180,"minecraft:fall_one_cm":22703,"minecraft:fly_one_cm":315830,"minecraft:player_kills":1},"minecraft:killed_by":{"minecraft:player":11},"minecraft:used":{"minecraft:golden_apple":4,"minecraft:stone_sword":3,"minecraft:light_blue_wool":207,"minecraft:oak_wood":16,"minecraft:iron_sword":38}},"DataVersion":3463}