{
  "minecraft:recipes/decorations/white_banner": {
    "criteria": {
      "has_white_wool": "2024-10-18 10:24:03 +0300"
    },
    "done": true
  },
  "minecraft:recipes/decorations/painting": {
    "criteria": {
      "has_wool": "2024-10-18 10:24:03 +0300"
    },
    "done": true
  },
  "minecraft:recipes/decorations/crafting_table": {
    "criteria": {
      "unlock_right_away": "2024-10-18 10:23:50 +0300"
    },
    "done": true
  },
  "minecraft:adventure/adventuring_time": {
    "criteria": {
      "minecraft:old_growth_pine_taiga": "2024-10-18 10:24:02 +0300",
      "minecraft:plains": "2024-10-18 10:23:51 +0300"
    },
    "done": false
  },
  "minecraft:recipes/decorations/white_bed": {
    "criteria": {
      "has_white_wool": "2024-10-18 10:24:03 +0300"
    },
    "done": true
  },
  "minecraft:recipes/decorations/white_carpet": {
    "criteria": {
      "has_white_wool": "2024-10-18 10:24:03 +0300"
    },
    "done": true
  },
  "DataVersion": 3463
}